turques/__init__.py
turques-0.0.0.dist-info/LICENSE
turques-0.0.0.dist-info/METADATA
turques-0.0.0.dist-info/WHEEL
turques-0.0.0.dist-info/top_level.txt
turques-0.0.0.dist-info/RECORD
