Metadata-Version: 2.1
Name: turques
Version: 0.0.0
Summary: Turkish question answering and generation tool.
Home-page: https://github.com/fcakyon/turques
Author: 
License: MIT
Keywords: machine-learning,deep-learning,ml,pytorch,NLP,question-answering,question-generation
Platform: UNKNOWN
Classifier: Development Status :: 5 - Production/Stable
Classifier: Operating System :: OS Independent
Classifier: Intended Audience :: Developers
Classifier: Intended Audience :: Science/Research
Classifier: Programming Language :: Python :: 3
Classifier: Programming Language :: Python :: 3.7
Classifier: Programming Language :: Python :: 3.8
Classifier: Programming Language :: Python :: 3.9
Classifier: Topic :: Software Development :: Libraries
Classifier: Topic :: Software Development :: Libraries :: Python Modules
Classifier: Topic :: Education
Classifier: Topic :: Scientific/Engineering
Classifier: Topic :: Scientific/Engineering :: Artificial Intelligence
Requires-Python: >=3.7
Requires-Dist: datasets (>=1.8.0)
Requires-Dist: nltk
Requires-Dist: protobuf (>=3.17.3)
Requires-Dist: pyyaml
Requires-Dist: rouge-score (==0.0.4)
Requires-Dist: sentencepiece
Requires-Dist: torch
Requires-Dist: transformers (>=4.0.0)
